Metadata-Version: 2.1
Name: quantum-sg
Version: 0.1.0
Summary: A command line tool that generates a cryptographically secure quantum-level secrets using ANU QRNG.
Home-page: https://github.com/alxshelepenok/quantum-sg
Author: Alexander Shelepenok
Author-email: alxshelepenok@gmail.com
Keywords: quantum random secrets
Classifier: Development Status :: 5 - Production/Stable
Classifier: License :: OSI Approved :: MIT License
Classifier: Topic :: Scientific/Engineering :: Mathematics
Classifier: Programming Language :: Python
Classifier: Programming Language :: Python :: 3
License-File: LICENSE
